pyros_interfaces_ros/__init__.py
pyros_interfaces_ros/__main__.py
pyros_interfaces_ros/_version.py
pyros_interfaces_ros/baseinterface.py
pyros_interfaces_ros/config.py
pyros_interfaces_ros/connection_cache_utils.py
pyros_interfaces_ros/deffile.py
pyros_interfaces_ros/definitions.py
pyros_interfaces_ros/exceptions.py
pyros_interfaces_ros/message_conversion.py
pyros_interfaces_ros/param_if.py
pyros_interfaces_ros/param_if_pool.py
pyros_interfaces_ros/poolparam.py
pyros_interfaces_ros/publisher_if.py
pyros_interfaces_ros/publisher_if_pool.py
pyros_interfaces_ros/pyros_ros.py
pyros_interfaces_ros/ros_interface.py
pyros_interfaces_ros/ros_loader.py
pyros_interfaces_ros/service_if.py
pyros_interfaces_ros/service_if_pool.py
pyros_interfaces_ros/subscriber_if.py
pyros_interfaces_ros/subscriber_if_pool.py
pyros_interfaces_ros/topicbase.py
pyros_interfaces_ros/util.py
pyros_interfaces_ros/api/__init__.py
pyros_interfaces_ros/api/rosgraph_safe.py
pyros_interfaces_ros/api/roslaunch_safe.py
pyros_interfaces_ros/api/roslib_safe.py
pyros_interfaces_ros/api/rosnode_safe.py
pyros_interfaces_ros/api/rospy_safe.py
pyros_interfaces_ros/rostests/__init__.py
pyros_interfaces_ros/rostests/testRosInterface.py
pyros_interfaces_ros/rostests/testService.py
pyros_interfaces_ros/rostests/testStringPublisher.py
pyros_interfaces_ros/rostests/testStringSubscriber.py
pyros_interfaces_ros/rostests/test_param_if_pool.py
pyros_interfaces_ros/rostests/test_publisher_if_pool.py
pyros_interfaces_ros/rostests/test_service_if_pool.py
pyros_interfaces_ros/rostests/test_subscriber_if_pool.py
pyros_interfaces_ros/tests/__init__.py
pyros_interfaces_ros/tests/testMsgConversion.py
pyros_interfaces_ros/tests/testPyrosROS.py
pyros_interfaces_ros/tests/testSignalHandling.py
pyros_interfaces_ros-0.4.2.dist-info/METADATA
pyros_interfaces_ros-0.4.2.dist-info/RECORD
pyros_interfaces_ros-0.4.2.dist-info/WHEEL
pyros_interfaces_ros-0.4.2.dist-info/top_level.txt
