Metadata-Version: 2.1
Name: pyros-interfaces-ros
Version: 0.4.2
Summary: Pyros ROS interface to provide ROS introspection for non-ROS users.
Home-page: http://github.com/asmodehn/pyros-rosinterface
Author: AlexV
Author-email: asmodehn@gmail.com
License: BSD
Platform: UNKNOWN
Requires-Dist: tblib
Requires-Dist: six
Requires-Dist: pyzmq
Requires-Dist: pyzmp (>=0.0.17)
Requires-Dist: pyros-config (>=0.2.0)
Requires-Dist: pyros-common (>=0.5.3)
Requires-Dist: click
Requires-Dist: nose (>=1.3.7)
Requires-Dist: mock (==1.0.1)
